rcbm/__init__.py
rcbm/fab.py
rcbm/htuse.py
rcbm/vent.py
rcbm-0.2.3.dist-info/LICENSE
rcbm-0.2.3.dist-info/WHEEL
rcbm-0.2.3.dist-info/METADATA
rcbm-0.2.3.dist-info/RECORD
