Metadata-Version: 2.1
Name: rcbm
Version: 0.2.3
Summary: A Resistance Capacitance (RC) Model for the Simulation of Building Stock Energy Usage
Home-page: https://github.com/codema-dev/rc-building-model
License: MIT
Author: Rowan Molony
Author-email: rowan.molony@codema.ie
Requires-Python: >=3.7,<4.0
Classifier: License :: OSI Approved :: MIT License
Classifier: Programming Language :: Python :: 3
Classifier: Programming Language :: Python :: 3.10
Classifier: Programming Language :: Python :: 3.7
Classifier: Programming Language :: Python :: 3.8
Classifier: Programming Language :: Python :: 3.9
Requires-Dist: pandas (>=1.0,<2.0)
Requires-Dist: pandas-stubs (>=1.2,<2.0)
Requires-Dist: pandera (>=0.7.2,<0.8.0)
Project-URL: Repository, https://github.com/codema-dev/rc-building-model
